qc_parallelizer/__init__.py
qc_parallelizer/base.py
qc_parallelizer/packers.py
qc_parallelizer/parallelizer.py
qc_parallelizer/bins/circuitbin.py
qc_parallelizer/bins/manager.py
qc_parallelizer/extensions/__init__.py
qc_parallelizer/extensions/backend.py
qc_parallelizer/extensions/circuit.py
qc_parallelizer/extensions/typing.py
qc_parallelizer/results/paralleljob.py
qc_parallelizer/results/postprocessing.py
qc_parallelizer/results/visualization.py
qc_parallelizer/util/__init__.py
qc_parallelizer/util/layouts.py
qc_parallelizer/util/logging.py
qc_parallelizer/util/translation.py
qc_parallelizer-1.3.2.dist-info/licenses/LICENSE
qc_parallelizer-1.3.2.dist-info/METADATA
qc_parallelizer-1.3.2.dist-info/WHEEL
qc_parallelizer-1.3.2.dist-info/top_level.txt
qc_parallelizer-1.3.2.dist-info/RECORD
